langgraph_cli/__init__.py
langgraph_cli/analytics.py
langgraph_cli/cli.py
langgraph_cli/config.py
langgraph_cli/constants.py
langgraph_cli/docker.py
langgraph_cli/exec.py
langgraph_cli/progress.py
langgraph_cli/py.typed
langgraph_cli/util.py
langgraph_cli/version.py
gigagraph_cli-0.1.52.dist-info/LICENSE
gigagraph_cli-0.1.52.dist-info/METADATA
gigagraph_cli-0.1.52.dist-info/WHEEL
gigagraph_cli-0.1.52.dist-info/entry_points.txt
gigagraph_cli-0.1.52.dist-info/RECORD
