Metadata-Version: 2.1
Name: gigagraph-cli
Version: 0.1.52
Summary: CLI for interacting with LangGraph API
Home-page: https://github.com/ai-forever/gigagraph
License: MIT
Requires-Python: >=3.9.0,<4.0.0
Classifier: License :: OSI Approved :: MIT License
Classifier: Programming Language :: Python :: 3
Classifier: Programming Language :: Python :: 3.9
Classifier: Programming Language :: Python :: 3.10
Classifier: Programming Language :: Python :: 3.11
Classifier: Programming Language :: Python :: 3.12
Requires-Dist: click (>=8.1.7,<9.0.0)
Project-URL: Repository, https://github.com/ai-forever/gigagraph
